larousse_api/__init__.py
larousse_api/larousse.py
larousse_api_sunbro-0.0.5.dist-info/LICENSE
larousse_api_sunbro-0.0.5.dist-info/METADATA
larousse_api_sunbro-0.0.5.dist-info/WHEEL
larousse_api_sunbro-0.0.5.dist-info/top_level.txt
larousse_api_sunbro-0.0.5.dist-info/RECORD
