Metadata-Version: 2.1
Name: larousse-api-sunbro
Version: 0.0.5
Summary: UNKNOWN
Home-page: https://github.com/quentin-dev/larousse_api
Author: Quentin Barbarat
Author-email: q.barbarat@gmail.com
License: UNKNOWN
Platform: UNKNOWN
Classifier: Programming Language :: Python :: 3
Classifier: License :: OSI Approved :: MIT License
Classifier: Operating System :: OS Independent
Requires-Python: >=3.7
Requires-Dist: requests (>=2.22.0)
Requires-Dist: bs4 (>=0.0.1)
